albu_spec/__init__.py
albu_spec/docstring_parser.py
albu_spec/extractor.py
albu_spec/models.py
albu_spec/py.typed
albu_spec/schema_parser.py
albu_spec/type_comparison.py
albu_spec/type_extraction.py
albu_spec/type_formatters.py
albu_spec/type_utils.py
albu_spec-0.0.3.dist-info/licenses/LICENSE
albu_spec-0.0.3.dist-info/METADATA
albu_spec-0.0.3.dist-info/WHEEL
albu_spec-0.0.3.dist-info/top_level.txt
albu_spec-0.0.3.dist-info/RECORD
