Metadata-Version: 2.4
Name: albu-spec
Version: 0.0.3
Summary: Extract comprehensive metadata from Albumentations transforms including parameters, types, constraints, and docstrings
Author-email: Vladimir Iglovikov <vladimir@albumentations.ai>
License: AGPL-3.0-or-later OR Commercial
Project-URL: Homepage, https://github.com/albumentations-team/albu-spec
Project-URL: Repository, https://github.com/albumentations-team/albu-spec
Project-URL: Documentation, https://github.com/albumentations-team/albu-spec#readme
Keywords: albumentations,metadata,computer-vision,augmentation,transforms
Classifier: Development Status :: 3 - Alpha
Classifier: Intended Audience :: Developers
Classifier: Intended Audience :: Science/Research
Classifier: License :: OSI Approved :: GNU Affero General Public License v3 or later (AGPLv3+)
Classifier: Operating System :: OS Independent
Classifier: Programming Language :: Python :: 3
Classifier: Programming Language :: Python :: 3.10
Classifier: Programming Language :: Python :: 3.11
Classifier: Programming Language :: Python :: 3.12
Classifier: Programming Language :: Python :: 3.13
Classifier: Topic :: Scientific/Engineering :: Image Processing
Classifier: Topic :: Software Development :: Libraries :: Python Modules
Requires-Python: >=3.10
License-File: LICENSE
Requires-Dist: pydantic>=2.0
Requires-Dist: google-docstring-parser>=0.0.9
Requires-Dist: typing-extensions>=4.0
Requires-Dist: albumentationsx
Requires-Dist: opencv-python-headless
Provides-Extra: dev
Requires-Dist: pytest>=7.0; extra == "dev"
Requires-Dist: pytest-cov>=4.0; extra == "dev"
Requires-Dist: ruff>=0.1.0; extra == "dev"
Requires-Dist: mypy>=1.0; extra == "dev"
Requires-Dist: albumentationsx; extra == "dev"
Dynamic: license-file
